{"/appartement/huren/delft/coenderstraat/46253160":{"distance":0,"hasDetails":true,"bedroomCount":1,"peopleCount":1,"price":850,"roomPrice":850,"responded":false,"concerningTexts":[],"suitable":false,"email":"info@deblooisvastgoed.nl","title":"Appartement Coenderstraat"},"/appartement/huren/delft/van-embdenstraat/46253067":{"distance":0,"hasDetails":true,"bedroomCount":2,"peopleCount":2,"price":1395,"roomPrice":697.5,"responded":true,"concerningTexts":[],"suitable":true,"email":"rotterdam@verrarealestate.com","title":"Appartement Van Embdenstraat"},"/appartement/huren/delft/oude-delft/46251975":{"distance":0,"hasDetails":true,"bedroomCount":2,"peopleCount":2,"price":2750,"roomPrice":1375,"responded":false,"concerningTexts":[],"suitable":false,"email":"info@vanhaarenvastgoed.nl","title":"Appartement Oude Delft"},"/appartement/huren/delft/nieuwe-plantage/46251814":{"distance":0,"hasDetails":true,"bedroomCount":1,"peopleCount":1,"price":800,"roomPrice":800,"responded":false,"concerningTexts":[],"suitable":false,"email":"delft@behome.nl","title":"Appartement Nieuwe Plantage"},"/appartement/huren/delft/verwersdijk/46251010":{"distance":0,"hasDetails":true,"bedroomCount":0,"peopleCount":1,"price":1450,"roomPrice":1450,"responded":false,"concerningTexts":[],"suitable":false,"email":"delft@rotsvast.nl","title":"Appartement Verwersdijk"},"/appartement/huren/delft/noordeinde/46249262":{"distance":0,"hasDetails":true,"bedroomCount":3,"peopleCount":3,"price":1975,"roomPrice":658.3333333333334,"responded":true,"concerningTexts":[],"suitable":true,"email":"info@doenmakelaars.com","title":"Appartement Noordeinde"},"/appartement/huren/delft/verwersdijk/46248679":{"distance":0,"hasDetails":true,"bedroomCount":2,"peopleCount":2,"price":1650,"roomPrice":825,"responded":false,"concerningTexts":[],"suitable":false,"email":"info@oudedelft.com","title":"Appartement Verwersdijk"},"/appartement/huren/delft/martinus-nijhofflaan/46246752":{"distance":0,"hasDetails":true,"bedroomCount":2,"peopleCount":2,"price":2900,"roomPrice":1450,"responded":false,"concerningTexts":[],"suitable":false,"email":"denhaag@verrarealestate.com","title":"Appartement Martinus Nijhofflaan"},"/appartement/huren/delft/achterom/46242382":{"distance":0,"hasDetails":true,"bedroomCount":1,"peopleCount":1,"price":1350,"roomPrice":1350,"responded":false,"concerningTexts":[],"suitable":false,"email":"delft@rotsvast.nl","title":"Appartement Achterom"},"/appartement/huren/delft/vrouwenregt/46234671":{"distance":0,"hasDetails":true,"bedroomCount":1,"peopleCount":1,"price":1100,"roomPrice":1100,"responded":false,"concerningTexts":[{"index":27,"concerningText":"couple","concerningSentence":"Units are for 1 person (no couples or family’s)"}],"suitable":false,"email":"info@svdmakelaars.nl","title":"Appartement Vrouwenregt"},"/appartement/huren/rijswijk/prof-meijerslaan/46246537":{"distance":2,"hasDetails":true,"bedroomCount":1,"peopleCount":1,"price":1195,"roomPrice":1195,"responded":false,"concerningTexts":[],"suitable":false,"email":"info@homelandmail.nl","title":"Appartement Prof. Meijerslaan"},"/appartement/huren/den-haag/steentijdsingel/46248455":{"distance":2,"hasDetails":true,"bedroomCount":2,"peopleCount":2,"price":1145,"roomPrice":572.5,"responded":true,"concerningTexts":[],"suitable":true,"email":"info@schielandborsboom.nl","title":"Appartement Steentijdsingel"},"/appartement/huren/den-haag/zevenwoudenlaan/46242444":{"distance":2,"hasDetails":true,"bedroomCount":3,"peopleCount":3,"price":1276,"roomPrice":425.3333333333333,"responded":true,"concerningTexts":[],"suitable":true,"email":"info@vbtverhuurmakelaars.nl","title":"Appartement Zevenwoudenlaan"},"/appartement/huren/den-haag/van-zeggelenlaan/46252709":{"distance":3,"hasDetails":true,"bedroomCount":2,"peopleCount":2,"price":1075,"roomPrice":537.5,"responded":true,"concerningTexts":[],"suitable":true,"email":"info@070wonen.nl","title":"Appartement Van Zeggelenlaan"},"/appartement/huren/den-haag/de-lannoystraat/46204589":{"distance":3,"hasDetails":true,"bedroomCount":2,"peopleCount":2,"price":1345,"roomPrice":672.5,"responded":true,"concerningTexts":[],"suitable":true,"email":"info@woon-match.nl","title":"Appartement De Lannoystraat"},"/appartement/huren/rijswijk/hendrik-ravesteijnplein/46192219":{"distance":3,"hasDetails":true,"bedroomCount":3,"peopleCount":3,"price":1500,"roomPrice":500,"responded":true,"suitable":true,"email":"info@homelandmail.nl","concerningTexts":[],"title":"Appartement Hendrik Ravesteijnplein"},"/appartement/huren/den-haag/1e-van-der-kunstraat/46252892":{"distance":4,"hasDetails":true,"bedroomCount":1,"peopleCount":1,"price":850,"roomPrice":850,"responded":false,"concerningTexts":[{"index":4,"concerningText":"student","concerningSentence":"000 studenten), Mondriaan college, het grootste overdekte winkelcentrum van den haag (de megastores) en vele nieuwe kantoren en woningen"}],"suitable":false,"email":"info@rentvalley.nl","title":"Appartement 1e Van der Kunstraat"},"/appartement/huren/den-haag/pasteurstraat/46252679":{"distance":4,"hasDetails":true,"bedroomCount":2,"peopleCount":2,"price":1100,"roomPrice":550,"responded":true,"concerningTexts":[],"suitable":true,"email":"home@number12.nl","title":"Appartement Pasteurstraat"},"/appartement/huren/den-haag/1e-van-der-kunstraat/46252424":{"distance":4,"hasDetails":true,"bedroomCount":1,"peopleCount":1,"price":860,"roomPrice":860,"responded":false,"concerningTexts":[{"index":4,"concerningText":"student","concerningSentence":"000 studenten), Mondriaan college, het grootste overdekte winkelcentrum van den haag (de megastores) en vele nieuwe kantoren en woningen"}],"suitable":false,"email":"info@rentvalley.nl","title":"Appartement 1e Van der Kunstraat"},"/appartement/huren/den-haag/koopmans-van-boekerenstraat/46213070":{"distance":4,"hasDetails":true,"bedroomCount":2,"peopleCount":2,"price":1195,"roomPrice":597.5,"responded":true,"concerningTexts":[],"suitable":true,"email":"info@immovita.nl","title":"Appartement Koopmans van Boekerenstraat"},"/appartement/huren/den-haag/1e-lulofsdwarsstraat/46211990":{"distance":4,"hasDetails":true,"bedroomCount":1,"peopleCount":1,"price":850,"roomPrice":850,"responded":false,"concerningTexts":[],"suitable":false,"email":"home@number12.nl","title":"Appartement 1e Lulofsdwarsstraat"},"/appartement/huren/den-haag/soestdijksekade/46234474":{"distance":4,"hasDetails":true,"bedroomCount":3,"peopleCount":3,"price":1375,"roomPrice":458.3333333333333,"responded":true,"suitable":true,"email":"info@immovita.nl","concerningTexts":[],"title":"Appartement Soestdijksekade"},"/appartement/huren/rijswijk/geestbrugweg/46250626":{"distance":4,"hasDetails":true,"bedroomCount":3,"peopleCount":3,"price":1795,"roomPrice":598.3333333333334,"responded":true,"concerningTexts":[],"suitable":true,"email":"home@number12.nl","title":"Appartement Geestbrugweg"},"/appartement/huren/den-haag/lyonnetstraat/46250500":{"distance":4,"hasDetails":true,"bedroomCount":3,"peopleCount":3,"price":1050,"roomPrice":350,"responded":true,"concerningTexts":[],"suitable":true,"email":"home@number12.nl","title":"Appartement Lyonnetstraat"},"/appartement/huren/den-haag/piet-paaltjensstraat/46251603":{"distance":4,"hasDetails":true,"bedroomCount":2,"peopleCount":2,"price":1195,"roomPrice":597.5,"responded":true,"concerningTexts":[],"suitable":true,"email":"home@number12.nl","title":"Appartement Piet Paaltjensstraat"},"/appartement/huren/den-haag/troelstrakade/46248943":{"distance":4,"hasDetails":true,"bedroomCount":3,"peopleCount":3,"price":1395,"roomPrice":465,"responded":true,"concerningTexts":[],"suitable":true,"email":"info@jjh-vastgoedbeheer.nl","title":"Appartement Troelstrakade"},"/appartement/huren/den-haag/uitgeeststraat/46248148":{"distance":4,"hasDetails":true,"bedroomCount":3,"peopleCount":3,"price":1395,"roomPrice":465,"responded":true,"suitable":true,"email":"info@homelandmail.nl","concerningTexts":[],"title":"Appartement Uitgeeststraat"},"/appartement/huren/den-haag/binckhorstlaan/46241235":{"distance":4,"hasDetails":true,"bedroomCount":1,"peopleCount":1,"price":1250,"roomPrice":1250,"responded":false,"concerningTexts":[],"suitable":false,"email":"denhaag@tweelwonen.nl","title":"Appartement Binckhorstlaan"},"/appartement/huren/den-haag/binckhorstlaan/46241119":{"distance":4,"hasDetails":true,"bedroomCount":1,"peopleCount":1,"price":1250,"roomPrice":1250,"responded":false,"concerningTexts":[],"suitable":false,"email":"denhaag@tweelwonen.nl","title":"Appartement Binckhorstlaan"},"/appartement/huren/den-haag/harderwijkstraat/46245777":{"distance":4,"hasDetails":true,"bedroomCount":2,"peopleCount":2,"price":995,"roomPrice":497.5,"responded":true,"concerningTexts":[],"suitable":true,"email":"home@number12.nl","title":"Appartement Harderwijkstraat"},"/appartement/huren/rotterdam/pieter-de-raadtstraat/46252048":{"distance":5,"hasDetails":true,"bedroomCount":1,"peopleCount":1,"price":875,"roomPrice":875,"responded":false,"concerningTexts":[],"suitable":false,"email":"verhuur@kolpavvs.nl","title":"Appartement Pieter de Raadtstraat"},"/appartement/huren/rotterdam/statenweg/46252056":{"distance":5,"hasDetails":true,"bedroomCount":2,"peopleCount":2,"price":1195,"roomPrice":597.5,"responded":true,"suitable":true,"email":"verhuur@kolpavvs.nl","concerningTexts":[],"title":"Appartement Statenweg"},"/appartement/huren/rotterdam/troelstrastraat/46251812":{"distance":5,"hasDetails":true,"bedroomCount":2,"peopleCount":2,"price":1495,"roomPrice":747.5,"responded":true,"suitable":true,"email":"info@rivarentals.com","concerningTexts":[],"title":"Appartement Troelstrastraat"},"/appartement/huren/rotterdam/cleyburchstraat/46251813":{"distance":5,"hasDetails":true,"bedroomCount":2,"peopleCount":2,"price":1450,"roomPrice":725,"responded":true,"suitable":true,"email":"info@rivarentals.com","concerningTexts":[],"title":"Appartement Cleyburchstraat"},"/appartement/huren/den-haag/amsterdamse-veerkade/46250789":{"distance":5,"hasDetails":true,"bedroomCount":1,"peopleCount":1,"price":950,"roomPrice":950,"responded":false,"concerningTexts":[],"suitable":false,"email":"info@rentvalley.nl","title":"Appartement Amsterdamse Veerkade"},"/appartement/huren/rotterdam/walenburgerweg/46250349":{"distance":5,"hasDetails":true,"bedroomCount":1,"peopleCount":1,"price":1495,"roomPrice":1495,"responded":false,"concerningTexts":[{"index":13,"concerningText":"student","concerningSentence":"If you are a student we need a school registration, employment agreement, salary slips of the guarantor, and a copy of the ID of your guarantor and yourself"}],"suitable":false,"email":"info@rivarentals.com","title":"Appartement Walenburgerweg"},"/appartement/huren/den-haag/celsiusstraat/46245699":{"distance":5,"hasDetails":true,"bedroomCount":2,"peopleCount":2,"price":1350,"roomPrice":675,"responded":true,"suitable":true,"email":"info@immovita.nl","concerningTexts":[],"title":"Appartement Celsiusstraat"},"/appartement/huren/rotterdam/bergstraat/46245523":{"distance":5,"hasDetails":true,"bedroomCount":2,"peopleCount":2,"price":1450,"roomPrice":725,"responded":true,"concerningTexts":[],"suitable":true,"email":"rotterdam@voorberg.nl","title":"Appartement Bergstraat"},"/appartement/huren/rotterdam/lisstraat/46236712":{"distance":5,"hasDetails":true,"bedroomCount":2,"peopleCount":2,"price":1350,"roomPrice":675,"responded":true,"concerningTexts":[],"suitable":true,"email":"rotterdam@tweelwonen.nl","title":"Appartement Lisstraat"},"/appartement/huren/rotterdam/lisstraat/46236525":{"distance":5,"hasDetails":true,"bedroomCount":2,"peopleCount":2,"price":1350,"roomPrice":675,"responded":true,"concerningTexts":[],"suitable":true,"email":"rotterdam@tweelwonen.nl","title":"Appartement Lisstraat"},"/appartement/huren/den-haag/thorbeckelaan/46236463":{"distance":5,"hasDetails":true,"bedroomCount":2,"peopleCount":2,"price":2000,"roomPrice":1000,"responded":false,"concerningTexts":[],"suitable":false,"email":"info@lutzrealestate.nl","title":"Appartement Thorbeckelaan"},"/appartement/huren/rotterdam/stadhoudersweg/46247152":{"distance":5,"hasDetails":true,"bedroomCount":1,"peopleCount":1,"price":1200,"roomPrice":1200,"responded":false,"concerningTexts":[],"suitable":false,"email":"verhuur@kolpavvs.nl","title":"Appartement Stadhoudersweg"},"/appartement/huren/rotterdam/noorderhavenkade/46228397":{"distance":5,"hasDetails":true,"bedroomCount":1,"peopleCount":1,"price":1495,"roomPrice":1495,"responded":false,"concerningTexts":[],"suitable":false,"email":"rotterdam@tweelwonen.nl","title":"Appartement Noorderhavenkade"},"/appartement/huren/rotterdam/gladiolusstraat/46187208":{"distance":5,"hasDetails":true,"bedroomCount":3,"peopleCount":3,"price":1800,"roomPrice":600,"responded":true,"suitable":true,"email":"linda@lindahousing.com","concerningTexts":[],"title":"Appartement Gladiolusstraat"},"/appartement/huren/rotterdam/stadhoudersweg/46189689":{"distance":5,"hasDetails":true,"bedroomCount":2,"peopleCount":2,"price":1375,"roomPrice":687.5,"responded":true,"concerningTexts":[],"suitable":true,"email":"info@woon-match.nl","title":"Appartement Stadhoudersweg"},"/appartement/huren/rotterdam/schiekade/46189735":{"distance":5,"hasDetails":true,"bedroomCount":1,"peopleCount":1,"price":1075,"roomPrice":1075,"responded":false,"concerningTexts":[],"suitable":false,"email":"info@woon-match.nl","title":"Appartement Schiekade"},"/appartement/huren/rotterdam/schieweg/46251630":{"distance":5,"hasDetails":true,"bedroomCount":1,"peopleCount":1,"price":1195,"roomPrice":1195,"responded":false,"concerningTexts":[{"index":13,"concerningText":"student","concerningSentence":"If you are a student we need a school registration, employment agreement, salary slips of the guarantor, and a copy of the ID of your guarantor and yourself"}],"suitable":false,"email":"info@rivarentals.com","title":"Appartement Schieweg"},"/appartement/huren/den-haag/kornoeljestraat/46251587":{"distance":5,"hasDetails":true,"bedroomCount":2,"peopleCount":2,"price":1650,"roomPrice":825,"responded":false,"concerningTexts":[],"suitable":false,"email":"rentals@trechousing.nl","title":"Appartement Kornoeljestraat"},"/appartement/huren/berkel-en-rodenrijs/parkstraat/46251532":{"distance":5,"hasDetails":true,"bedroomCount":3,"peopleCount":3,"price":1595,"roomPrice":531.6666666666666,"responded":true,"concerningTexts":[],"suitable":true,"email":"info@rentanapartment.nl","title":"Appartement Parkstraat"},"/appartement/huren/rotterdam/statensingel/46249113":{"distance":5,"hasDetails":true,"bedroomCount":1,"peopleCount":1,"price":1350,"roomPrice":1350,"responded":false,"concerningTexts":[],"suitable":false,"email":"verhuur@kolpavvs.nl","title":"Appartement Statensingel"},"/appartement/huren/rotterdam/lisstraat/46223259":{"distance":5,"hasDetails":true,"bedroomCount":2,"peopleCount":2,"price":1500,"roomPrice":750,"responded":true,"concerningTexts":[],"suitable":true,"email":"info@realestate.nl","title":"Appartement Lisstraat"},"/appartement/huren/rotterdam/lisstraat/46223260":{"distance":5,"hasDetails":true,"bedroomCount":2,"peopleCount":2,"price":1500,"roomPrice":750,"responded":true,"concerningTexts":[],"suitable":true,"email":"info@realestate.nl","title":"Appartement Lisstraat"},"/appartement/huren/den-haag/binckhorstlaan/46219209":{"distance":5,"hasDetails":true,"bedroomCount":1,"peopleCount":1,"price":1500,"roomPrice":1500,"responded":false,"concerningTexts":[{"index":157,"concerningText":"student","concerningSentence":"De appartementen zijn onderdeel van een hotel dat een concept heeft dat het beste biedt van zowel een kort verblijf voor toeristen en een lang verblijf voor studenten, expats of iedereen die past bij ons unieke concept en hotel ervaring"},{"index":129,"concerningText":"student","concerningSentence":"The apartments are part of a hotel that has a concept that offers the best of both a short stay for tourists and a long stay for students, expats or anyone that fits our unique concept and hotel experience"}],"suitable":false,"email":"verhuur@vanderhuizen.com","title":"Appartement Binckhorstlaan"},"/appartement/huren/rotterdam/schieweg/46211545":{"distance":5,"hasDetails":true,"bedroomCount":1,"peopleCount":1,"price":1150,"roomPrice":1150,"responded":false,"concerningTexts":[],"suitable":false,"email":"info@realestate.nl","title":"Appartement Schieweg"},"/appartement/huren/rotterdam/roo-valkstraat/46211044":{"distance":5,"hasDetails":true,"bedroomCount":2,"peopleCount":2,"price":1100,"roomPrice":550,"responded":true,"suitable":true,"email":"verhuur@kolpavvs.nl","concerningTexts":[],"title":"Appartement Roo-Valkstraat"},"/appartement/huren/rotterdam/insulindestraat/46207158":{"distance":5,"hasDetails":true,"bedroomCount":1,"peopleCount":1,"price":1100,"roomPrice":1100,"responded":false,"concerningTexts":[],"suitable":false,"email":"info@randstadhousing.nl","title":"Appartement Insulindestraat"},"/appartement/huren/rotterdam/walenburgerweg/46245872":{"distance":5,"hasDetails":true,"bedroomCount":2,"peopleCount":2,"price":1650,"roomPrice":825,"responded":false,"concerningTexts":[{"index":18,"concerningText":"student","concerningSentence":"Ideal for expats, students, singles and couples"},{"index":57,"concerningText":"student","concerningSentence":"a beautiful apartment, ideal for a single or couple or 2 students, ready to move into"},{"index":40,"concerningText":"couple","concerningSentence":"Ideal for expats, students, singles and couples"},{"index":45,"concerningText":"couple","concerningSentence":"a beautiful apartment, ideal for a single or couple or 2 students, ready to move into"}],"suitable":false,"email":"info@fransenvastgoed.nl","title":"Appartement Walenburgerweg"},"/appartement/huren/den-haag/zuiderparklaan/46245873":{"distance":5,"hasDetails":true,"bedroomCount":3,"peopleCount":3,"price":1075,"roomPrice":358.3333333333333,"responded":true,"concerningTexts":[],"suitable":true,"email":"home@number12.nl","title":"Appartement Zuiderparklaan"},"/appartement/huren/den-haag/donker-curtiusstraat/46250201":{"distance":5,"hasDetails":true,"bedroomCount":2,"peopleCount":2,"price":1695,"roomPrice":847.5,"responded":false,"concerningTexts":[],"suitable":false,"email":"rentals@trechousing.nl","title":"Appartement Donker Curtiusstraat"},"/appartement/huren/rotterdam/vlaggemanstraat/46249934":{"distance":5,"hasDetails":true,"bedroomCount":3,"peopleCount":1,"price":1795,"roomPrice":1795,"responded":false,"concerningTexts":[{"index":12,"concerningText":"student","concerningSentence":"Inkomenseis studenten"},{"index":29,"concerningText":"student","concerningSentence":"Deze woning is geschikt voor studenten"},{"index":0,"concerningText":"Student","concerningSentence":"Studenten kunnen in aanmerking komen met een borgsteller of een met 1 á 2 maanden huur verhoogde waarborgsom"},{"index":19,"concerningText":"student","concerningSentence":"Income requirement students"},{"index":11,"concerningText":"student","concerningSentence":"Renting by students is possible"},{"index":0,"concerningText":"Student","concerningSentence":"Students can qualify with a guarantor or a deposit increased by 1 to 2 months' rent"},{"index":19,"concerningText":"sharer","concerningSentence":"Perfect for 3 home sharers"},{"index":19,"concerningText":"deler","concerningSentence":"Perfect voor woningdelers"}],"suitable":false,"email":"contact@perfectrent.nl","title":"Appartement Vlaggemanstraat"},"/appartement/huren/berkel-en-rodenrijs/parkstraat-26/46249747":{"distance":5,"hasDetails":true,"bedroomCount":3,"peopleCount":3,"price":1495,"roomPrice":498.3333333333333,"responded":true,"concerningTexts":[],"suitable":true,"email":"info@rentanapartment.nl","title":"Appartement Parkstraat 26"},"/appartement/huren/den-haag/mient/46242290":{"distance":5,"hasDetails":true,"bedroomCount":2,"peopleCount":2,"price":1450,"roomPrice":725,"responded":true,"concerningTexts":[],"suitable":true,"email":"info@homelandmail.nl","title":"Appartement Mient"},"/appartement/huren/den-haag/abrikozenstraat/46241457":{"distance":5,"hasDetails":true,"bedroomCount":2,"peopleCount":2,"price":1550,"roomPrice":775,"responded":false,"concerningTexts":[],"suitable":false,"email":"info@homelandmail.nl","title":"Appartement Abrikozenstraat"},"/appartement/huren/den-haag/brouwersgracht/46252430":{"distance":5,"hasDetails":true,"bedroomCount":1,"peopleCount":1,"price":1350,"roomPrice":1350,"responded":false,"concerningTexts":[],"suitable":false,"email":"rentals@trechousing.nl","title":"Appartement Brouwersgracht"},"/appartement/huren/den-haag/brouwersgracht/46252431":{"distance":5,"hasDetails":true,"bedroomCount":1,"peopleCount":1,"price":1350,"roomPrice":1350,"responded":false,"concerningTexts":[],"suitable":false,"email":"rentals@trechousing.nl","title":"Appartement Brouwersgracht"},"/appartement/huren/voorburg/huijgensstraat/46252415":{"distance":5,"hasDetails":true,"bedroomCount":1,"peopleCount":1,"price":1100,"roomPrice":1100,"responded":false,"concerningTexts":[],"suitable":false,"email":"info@immovita.nl","title":"Appartement Huijgensstraat"},"/appartement/huren/den-haag/brouwersgracht/46252037":{"distance":5,"hasDetails":true,"bedroomCount":1,"peopleCount":1,"price":1250,"roomPrice":1250,"responded":false,"concerningTexts":[],"suitable":false,"email":"rentals@trechousing.nl","title":"Appartement Brouwersgracht"},"/appartement/huren/den-haag/prinsegracht/46235597":{"distance":5,"hasDetails":true,"bedroomCount":4,"peopleCount":4,"price":1995,"roomPrice":498.75,"responded":true,"concerningTexts":[],"suitable":true,"email":"info@homelandmail.nl","title":"Appartement Prinsegracht"},"/appartement/huren/den-haag/westeinde/46253159":{"distance":6,"hasDetails":true,"bedroomCount":1,"peopleCount":1,"price":875,"roomPrice":875,"responded":false,"concerningTexts":[],"suitable":false,"email":"info@070wonen.nl","title":"Appartement Westeinde"},"/appartement/huren/rotterdam/provenierssingel/46253028":{"distance":6,"hasDetails":true,"bedroomCount":2,"peopleCount":2,"price":1495,"roomPrice":747.5,"responded":true,"concerningTexts":[],"suitable":true,"email":"info@rentanapartment.nl","title":"Appartement Provenierssingel"},"/appartement/huren/rotterdam/provenierssingel/46253029":{"distance":6,"hasDetails":true,"bedroomCount":2,"peopleCount":2,"price":1350,"roomPrice":675,"responded":true,"concerningTexts":[],"suitable":true,"email":"info@rentanapartment.nl","title":"Appartement Provenierssingel"},"/appartement/huren/rotterdam/provenierssingel/46253030":{"distance":6,"hasDetails":true,"bedroomCount":2,"peopleCount":2,"price":1695,"roomPrice":847.5,"responded":false,"concerningTexts":[],"suitable":false,"email":"info@rentanapartment.nl","title":"Appartement Provenierssingel"},"/appartement/huren/rotterdam/3e-pijnackerstraat/46253011":{"distance":6,"hasDetails":true,"bedroomCount":2,"peopleCount":2,"price":1095,"roomPrice":547.5,"responded":true,"suitable":true,"email":"info@rentanapartment.nl","concerningTexts":[],"title":"Appartement 3E Pijnackerstraat"},"/appartement/huren/den-haag/tweede-schuytstraat/46252495":{"distance":6,"hasDetails":true,"bedroomCount":1,"peopleCount":1,"price":1072,"roomPrice":1072,"responded":false,"concerningTexts":[],"suitable":false,"email":"info@cityhomes.nl","title":"Appartement Tweede Schuytstraat"},"/appartement/huren/rotterdam/schaatsbaan/46251974":{"distance":6,"hasDetails":true,"bedroomCount":2,"peopleCount":1,"price":1495,"roomPrice":1495,"responded":false,"concerningTexts":[{"index":12,"concerningText":"student","concerningSentence":"Inkomenseis studenten"},{"index":29,"concerningText":"student","concerningSentence":"Deze woning is geschikt voor studenten"},{"index":0,"concerningText":"Student","concerningSentence":"Studenten kunnen in aanmerking komen met een borgsteller of een met 1 á 2 maanden huur verhoogde waarborgsom"},{"index":19,"concerningText":"student","concerningSentence":"Income requirement students"},{"index":11,"concerningText":"student","concerningSentence":"Renting by students is possible"},{"index":0,"concerningText":"Student","concerningSentence":"Students can qualify with a guarantor or a deposit increased by 1 to 2 months' rent"},{"index":19,"concerningText":"sharer","concerningSentence":"Perfect for 2 home sharers"},{"index":21,"concerningText":"deler","concerningSentence":"Perfect voor 2 woningdelers"}],"suitable":false,"email":"contact@perfectrent.nl","title":"Appartement Schaatsbaan"},"/appartement/huren/rotterdam/bloklandstraat/46251892":{"distance":6,"hasDetails":true,"bedroomCount":1,"peopleCount":1,"price":1250,"roomPrice":1250,"responded":false,"concerningTexts":[],"suitable":false,"email":"info@jjh-vastgoedbeheer.nl","title":"Appartement Bloklandstraat"},"/appartement/huren/rotterdam/1e-middellandstraat/46252323":{"distance":6,"hasDetails":true,"bedroomCount":3,"peopleCount":3,"price":1115,"roomPrice":371.6666666666667,"responded":true,"concerningTexts":[],"suitable":true,"email":"info@jilldehaasmakelaardij.nl","title":"Appartement 1e Middellandstraat"},"/appartement/huren/rotterdam/kruisplein/46250637":{"distance":6,"hasDetails":true,"bedroomCount":2,"peopleCount":2,"price":1750,"roomPrice":875,"responded":false,"concerningTexts":[{"index":13,"concerningText":"student","concerningSentence":"If you are a student we need a school registration, employment agreement, salary slips of the guarantor, and a copy of the ID of your guarantor and yourself"}],"suitable":false,"email":"info@rivarentals.com","title":"Appartement Kruisplein"},"/appartement/huren/den-haag/schenkkade/46250512":{"distance":6,"hasDetails":true,"bedroomCount":3,"peopleCount":3,"price":1995,"roomPrice":665,"responded":true,"concerningTexts":[],"suitable":true,"email":"rentals@trechousing.nl","title":"Appartement Schenkkade"},"/appartement/huren/rotterdam/spiegelnisserstraat/46250373":{"distance":6,"hasDetails":true,"bedroomCount":1,"peopleCount":1,"price":1495,"roomPrice":1495,"responded":false,"concerningTexts":[],"suitable":false,"email":"utrecht@starthousing.nl","title":"Appartement Spiegelnisserstraat"},"/appartement/huren/den-haag/laan-van-nieuw-oost-indie/46248664":{"distance":6,"hasDetails":true,"bedroomCount":1,"peopleCount":1,"price":1550,"roomPrice":1550,"responded":false,"concerningTexts":[{"index":35,"concerningText":"couple","concerningSentence":"Available for a single person or a couple"}],"suitable":false,"email":"home@number12.nl","title":"Appartement Laan van Nieuw-Oost-Indie"},"/appartement/huren/den-haag/laan-van-nieuw-oost-indie/46248665":{"distance":6,"hasDetails":true,"bedroomCount":1,"peopleCount":1,"price":1595,"roomPrice":1595,"responded":false,"concerningTexts":[{"index":35,"concerningText":"couple","concerningSentence":"Available for a single person or a couple"}],"suitable":false,"email":"home@number12.nl","title":"Appartement Laan van Nieuw-Oost-Indie"},"/appartement/huren/den-haag/laan-van-nieuw-oost-indie/46248666":{"distance":6,"hasDetails":true,"bedroomCount":1,"peopleCount":1,"price":1650,"roomPrice":1650,"responded":false,"concerningTexts":[{"index":35,"concerningText":"couple","concerningSentence":"Available for a single person or a couple"}],"suitable":false,"email":"home@number12.nl","title":"Appartement Laan van Nieuw-Oost-Indie"},"/appartement/huren/rotterdam/oppert/46252944":{"distance":6,"hasDetails":true,"bedroomCount":2,"peopleCount":2,"price":1750,"roomPrice":875,"responded":false,"concerningTexts":[],"suitable":false,"email":"linda@lindahousing.com","title":"Appartement Oppert"},"/appartement/huren/rotterdam/kleiweg/46252893":{"distance":6,"hasDetails":true,"bedroomCount":2,"peopleCount":2,"price":1375,"roomPrice":687.5,"responded":true,"suitable":true,"email":"info@rivarentals.com","concerningTexts":[],"title":"Appartement Kleiweg"},"/appartement/huren/den-haag/oranjestraat/46243443":{"distance":6,"hasDetails":true,"bedroomCount":3,"peopleCount":3,"price":2085,"roomPrice":695,"responded":true,"concerningTexts":[],"suitable":true,"email":"info@immovita.nl","title":"Appartement Oranjestraat"},"/appartement/huren/den-haag/oranjestraat/46243178":{"distance":6,"hasDetails":true,"bedroomCount":2,"peopleCount":2,"price":2000,"roomPrice":1000,"responded":false,"concerningTexts":[],"suitable":false,"email":"info@i-re.nl","title":"Appartement Oranjestraat"},"/appartement/huren/rotterdam/kruisplein/46243147":{"distance":6,"hasDetails":true,"bedroomCount":2,"peopleCount":2,"price":2200,"roomPrice":1100,"responded":false,"concerningTexts":[],"suitable":false,"email":"info@tvnrealestate.nl","title":"Appartement Kruisplein"},"/appartement/huren/den-haag/oranjestraat/46242911":{"distance":6,"hasDetails":true,"bedroomCount":2,"peopleCount":2,"price":2000,"roomPrice":1000,"responded":false,"concerningTexts":[],"suitable":false,"email":"info@i-re.nl","title":"Appartement Oranjestraat"},"/appartement/huren/rotterdam/tollensstraat/46242887":{"distance":6,"hasDetails":true,"bedroomCount":3,"peopleCount":2,"price":1850,"roomPrice":925,"responded":false,"concerningTexts":[{"index":29,"concerningText":"student","concerningSentence":"delen van woning (collega’s, studenten)"},{"index":28,"concerningText":"student","concerningSentence":"sharing a home (colleagues, students)"},{"index":28,"concerningText":"student","concerningSentence":"sharing a home (colleagues, students)"}],"suitable":false,"email":"info@expatrentalscout.com","title":"Appartement Tollensstraat"},"/appartement/huren/rotterdam/kruisplein/46248531":{"distance":6,"hasDetails":true,"bedroomCount":1,"peopleCount":1,"price":1750,"roomPrice":1750,"responded":false,"concerningTexts":[],"suitable":false,"email":"info@tvnrealestate.nl","title":"Appartement Kruisplein"},"/appartement/huren/rotterdam/kruiskade/46248507":{"distance":6,"hasDetails":true,"bedroomCount":1,"peopleCount":1,"price":2200,"roomPrice":2200,"responded":false,"concerningTexts":[],"suitable":false,"email":"info@vhpn.nl","title":"Appartement Kruiskade"},"/appartement/huren/rotterdam/kruiskade/46248253":{"distance":6,"hasDetails":true,"bedroomCount":1,"peopleCount":1,"price":1300,"roomPrice":1300,"responded":false,"concerningTexts":[],"suitable":false,"email":"info@vhpn.nl","title":"Appartement Kruiskade"},"/appartement/huren/voorburg/ewoudt-van-der-dussenlaan/46248122":{"distance":6,"hasDetails":true,"bedroomCount":2,"peopleCount":2,"price":1095,"roomPrice":547.5,"responded":true,"concerningTexts":[],"suitable":true,"email":"home@number12.nl","title":"Appartement Ewoudt van der Dussenlaan"},"/appartement/huren/den-haag/gedempte-gracht/46247047":{"distance":6,"hasDetails":true,"bedroomCount":2,"peopleCount":2,"price":1995,"roomPrice":997.5,"responded":false,"concerningTexts":[],"suitable":false,"email":"rentals@trechousing.nl","title":"Appartement Gedempte Gracht"},"/appartement/huren/den-haag/laan-van-meerdervoort/46247026":{"distance":6,"hasDetails":true,"bedroomCount":2,"peopleCount":2,"price":1425,"roomPrice":712.5,"responded":true,"concerningTexts":[],"suitable":true,"email":"info@vestingvastgoed.nl","title":"Appartement Laan Van Meerdervoort"},"/appartement/huren/den-haag/korte-houtstraat/46246718":{"distance":6,"hasDetails":true,"bedroomCount":2,"peopleCount":2,"price":1400,"roomPrice":700,"responded":true,"concerningTexts":[],"suitable":true,"email":"info@rehofmakelaars.nl","title":"Appartement Korte Houtstraat"},"/appartement/huren/den-haag/suezkade/46246677":{"distance":6,"hasDetails":true,"bedroomCount":2,"peopleCount":2,"price":1995,"roomPrice":997.5,"responded":false,"concerningTexts":[],"suitable":false,"email":"rentals@trechousing.nl","title":"Appartement Suezkade"},"/appartement/huren/den-haag/hugo-de-grootstraat/46246598":{"distance":6,"hasDetails":true,"bedroomCount":4,"peopleCount":4,"price":2495,"roomPrice":623.75,"responded":true,"concerningTexts":[],"suitable":true,"email":"info@tvswonen.nl","title":"Appartement Hugo de Grootstraat"},"/appartement/huren/den-haag/weimarstraat/46246554":{"distance":6,"hasDetails":true,"bedroomCount":2,"peopleCount":2,"price":1895,"roomPrice":947.5,"responded":false,"concerningTexts":[],"suitable":false,"email":"info@homelandmail.nl","title":"Appartement Weimarstraat"},"/appartement/huren/den-haag/weimarstraat/46246539":{"distance":6,"hasDetails":true,"bedroomCount":2,"peopleCount":2,"price":1895,"roomPrice":947.5,"responded":false,"concerningTexts":[],"suitable":false,"email":"info@homelandmail.nl","title":"Appartement Weimarstraat"},"/appartement/huren/den-haag/korte-houtstraat/46246523":{"distance":6,"hasDetails":true,"bedroomCount":2,"peopleCount":2,"price":1400,"roomPrice":700,"responded":true,"concerningTexts":[],"suitable":true,"email":"info@rehofmakelaars.nl","title":"Appartement Korte Houtstraat"},"/appartement/huren/den-haag/hugo-de-grootstraat/46246446":{"distance":6,"hasDetails":true,"bedroomCount":4,"peopleCount":4,"price":2495,"roomPrice":623.75,"responded":true,"concerningTexts":[],"suitable":true,"email":"info@tvswonen.nl","title":"Appartement Hugo De Grootstraat"},"/appartement/huren/rotterdam/kruiskade/46130471":{"distance":6,"hasDetails":true,"bedroomCount":1,"peopleCount":1,"price":1550,"roomPrice":1550,"responded":false,"concerningTexts":[],"suitable":false,"email":"info@rentanapartment.nl","title":"Appartement Kruiskade"},"/appartement/huren/rotterdam/halvemaanpassage/46113457":{"distance":6,"hasDetails":true,"bedroomCount":2,"peopleCount":2,"price":2395,"roomPrice":1197.5,"responded":false,"concerningTexts":[],"suitable":false,"email":"info@jecorental.nl","title":"Appartement Halvemaanpassage"},"/appartement/huren/voorburg/van-alphenstraat/46247974":{"distance":6,"hasDetails":true,"bedroomCount":1,"peopleCount":1,"price":1095,"roomPrice":1095,"responded":false,"concerningTexts":[],"suitable":false,"email":"kantoor@woonzeker.com","title":"Appartement van Alphenstraat"},"/appartement/huren/den-haag/hugo-de-grootstraat/46246309":{"distance":6,"hasDetails":true,"bedroomCount":1,"peopleCount":1,"price":1395,"roomPrice":1395,"responded":false,"concerningTexts":[],"suitable":false,"email":"info@tvswonen.nl","title":"Appartement Hugo de Grootstraat"},"/appartement/huren/den-haag/hugo-de-grootstraat/46246124":{"distance":6,"hasDetails":true,"bedroomCount":1,"peopleCount":1,"price":1395,"roomPrice":1395,"responded":false,"concerningTexts":[],"suitable":false,"email":"info@tvswonen.nl","title":"Appartement Hugo de Grootstraat"},"/appartement/huren/rotterdam/beukelsweg/46245960":{"distance":6,"hasDetails":true,"bedroomCount":1,"peopleCount":1,"price":1250,"roomPrice":1250,"responded":false,"concerningTexts":[],"suitable":false,"email":"vliegenthartmakelaardij@gmail.com","title":"Appartement Beukelsweg"},"/appartement/huren/rotterdam/kruisplein/46247290":{"distance":6,"hasDetails":true,"bedroomCount":2,"peopleCount":2,"price":2500,"roomPrice":1250,"responded":false,"concerningTexts":[],"suitable":false,"email":"portsville@portsville.com","title":"Appartement Kruisplein"},"/appartement/huren/voorburg/van-alphenstraat/46247180":{"distance":6,"hasDetails":true,"bedroomCount":1,"peopleCount":1,"price":1095,"roomPrice":1095,"responded":false,"concerningTexts":[],"suitable":false,"email":"kantoor@woonzeker.com","title":"Appartement van Alphenstraat"},"/appartement/huren/den-haag/buijs-ballotstraat/46251554":{"distance":6,"hasDetails":true,"bedroomCount":1,"peopleCount":1,"price":1275,"roomPrice":1275,"responded":false,"concerningTexts":[],"suitable":false,"email":"info@immovita.nl","title":"Appartement Buijs Ballotstraat"},"/appartement/huren/rotterdam/hoogstraat/46251475":{"distance":6,"hasDetails":true,"bedroomCount":2,"peopleCount":2,"price":1495,"roomPrice":747.5,"responded":true,"suitable":true,"email":"info@rivarentals.com","concerningTexts":[],"title":"Appartement Hoogstraat"},"/appartement/huren/den-haag/laan-van-meerdervoort/46251756":{"distance":6,"hasDetails":true,"bedroomCount":1,"peopleCount":1,"price":670,"roomPrice":670,"responded":true,"suitable":true,"email":"info@immovita.nl","concerningTexts":[],"title":"Appartement Laan van Meerdervoort"},"/appartement/huren/rotterdam/kootsekade/46219779":{"distance":6,"hasDetails":true,"bedroomCount":2,"peopleCount":2,"price":1495,"roomPrice":747.5,"responded":false,"concerningTexts":[],"suitable":true,"email":"vliegenthartmakelaardij@gmail.com","title":"Appartement Kootsekade"},"/appartement/huren/rotterdam/halvemaanpassage/46216076":{"distance":6,"hasDetails":true,"bedroomCount":3,"peopleCount":3,"price":2900,"roomPrice":966.6666666666666,"responded":false,"concerningTexts":[],"suitable":false,"email":"info@rivarentals.com","title":"Appartement Halvemaanpassage"},"/appartement/huren/den-haag/laan-van-nieuw-oost-indie/46213166":{"distance":6,"hasDetails":true,"bedroomCount":1,"peopleCount":1,"price":1195,"roomPrice":1195,"responded":false,"concerningTexts":[],"suitable":false,"email":"info@immovita.nl","title":"Appartement Laan van Nieuw-Oost-Indie"},"/appartement/huren/rotterdam/noordplein/46243816":{"distance":6,"hasDetails":true,"bedroomCount":5,"peopleCount":5,"price":3000,"roomPrice":600,"responded":true,"concerningTexts":[],"suitable":true,"email":"info@rotterdamrent.com","title":"Appartement Noordplein"},"/appartement/huren/rotterdam/binnenrotte/46243798":{"distance":6,"hasDetails":true,"bedroomCount":3,"peopleCount":3,"price":2700,"roomPrice":900,"responded":false,"concerningTexts":[],"suitable":false,"email":"info@rotterdamrent.com","title":"Appartement Binnenrotte"},"/appartement/huren/den-haag/schenkkade/46243770":{"distance":6,"hasDetails":true,"bedroomCount":2,"peopleCount":2,"price":2495,"roomPrice":1247.5,"responded":false,"suitable":false,"email":"rentals@trechousing.nl","concerningTexts":[{"index":0,"concerningText":"Sharer","concerningSentence":"Sharers are not allowed unless they are two individuals"},{"index":0,"concerningText":"Sharer","concerningSentence":"Sharers are not allowed unless they are two individuals"}],"title":"Appartement Schenkkade"},"/appartement/huren/den-haag/gedempte-gracht/46243597":{"distance":6,"hasDetails":true,"bedroomCount":2,"peopleCount":2,"price":1850,"roomPrice":925,"responded":false,"concerningTexts":[],"suitable":false,"email":"rentals@trechousing.nl","title":"Appartement Gedempte Gracht"},"/appartement/huren/den-haag/daguerrestraat/46227901":{"distance":6,"hasDetails":true,"bedroomCount":1,"peopleCount":1,"price":900,"roomPrice":900,"responded":false,"concerningTexts":[],"suitable":false,"email":"home@number12.nl","title":"Appartement Daguerrestraat"},"/appartement/huren/den-haag/de-perponcherstraat/46250867":{"distance":6,"hasDetails":true,"bedroomCount":3,"peopleCount":3,"price":1275,"roomPrice":425,"responded":true,"concerningTexts":[],"suitable":true,"email":"info@rentvalley.nl","title":"Appartement De Perponcherstraat"},"/appartement/huren/rotterdam/noordplein/46237689":{"distance":6,"hasDetails":true,"bedroomCount":3,"peopleCount":3,"price":2300,"roomPrice":766.6666666666666,"responded":false,"concerningTexts":[],"suitable":false,"email":"info@rotterdamrent.com","title":"Appartement Noordplein"},"/appartement/huren/den-haag/usselincxstraat/46236780":{"distance":6,"hasDetails":true,"bedroomCount":2,"peopleCount":2,"price":1650,"roomPrice":825,"responded":false,"concerningTexts":[],"suitable":false,"email":"rentals@trechousing.nl","title":"Appartement Usselincxstraat"},"/appartement/huren/rotterdam/kruiskade/46184556":{"distance":6,"hasDetails":true,"bedroomCount":2,"peopleCount":2,"price":2065,"roomPrice":1032.5,"responded":false,"concerningTexts":[],"suitable":false,"email":"info@rentanapartment.nl","title":"Appartement Kruiskade"},"/appartement/huren/rotterdam/kruiskade/46184465":{"distance":6,"hasDetails":true,"bedroomCount":1,"peopleCount":1,"price":1650,"roomPrice":1650,"responded":false,"concerningTexts":[],"suitable":false,"email":"info@rentanapartment.nl","title":"Appartement Kruiskade"},"/appartement/huren/rotterdam/suze-groeneweglaan/46189692":{"distance":6,"hasDetails":true,"bedroomCount":1,"peopleCount":1,"price":1275,"roomPrice":1275,"responded":false,"concerningTexts":[],"suitable":false,"email":"info@woon-match.nl","title":"Appartement Suze Groeneweglaan"},"/appartement/huren/rotterdam/kruiskade/46176143":{"distance":6,"hasDetails":true,"bedroomCount":1,"peopleCount":1,"price":1250,"roomPrice":1250,"responded":false,"concerningTexts":[],"suitable":false,"email":"info@vhpn.nl","title":"Appartement Kruiskade"},"/appartement/huren/rotterdam/botersloot/46235502":{"distance":6,"hasDetails":true,"bedroomCount":1,"peopleCount":1,"price":1650,"roomPrice":1650,"responded":false,"concerningTexts":[],"suitable":false,"email":"info@jecorental.nl","title":"Appartement Botersloot"},"/appartement/huren/den-haag/usselincxstraat/46234677":{"distance":6,"hasDetails":true,"bedroomCount":2,"peopleCount":2,"price":1895,"roomPrice":947.5,"responded":false,"concerningTexts":[],"suitable":false,"email":"rentals@trechousing.nl","title":"Appartement Usselincxstraat"},"/appartement/huren/den-haag/passage/46245208":{"distance":6,"hasDetails":true,"bedroomCount":1,"peopleCount":1,"price":1375,"roomPrice":1375,"responded":false,"concerningTexts":[],"suitable":false,"email":"info@lutzrealestate.nl","title":"Appartement Passage"},"/appartement/huren/den-haag/vondelstraat/46244834":{"distance":6,"hasDetails":true,"bedroomCount":2,"peopleCount":2,"price":2250,"roomPrice":1125,"responded":false,"concerningTexts":[],"suitable":false,"email":"rentals@trechousing.nl","title":"Appartement Vondelstraat"},"/appartement/huren/rotterdam/molenwaterweg/46209907":{"distance":6,"hasDetails":true,"bedroomCount":2,"peopleCount":2,"price":1195,"roomPrice":597.5,"responded":true,"suitable":true,"email":"verhuur@kolpavvs.nl","concerningTexts":[],"title":"Appartement Molenwaterweg"},"/appartement/huren/rotterdam/goudsesingel/46208149":{"distance":6,"hasDetails":true,"bedroomCount":1,"peopleCount":1,"price":1350,"roomPrice":1350,"responded":false,"concerningTexts":[],"suitable":false,"email":"verhuur@kolpavvs.nl","title":"Appartement Goudsesingel"},"/appartement/huren/rotterdam/herman-robbersstraat/46239647":{"distance":6,"hasDetails":true,"bedroomCount":1,"peopleCount":1,"price":1495,"roomPrice":1495,"responded":false,"concerningTexts":[],"suitable":false,"email":"info@rentanapartment.nl","title":"Appartement Herman Robbersstraat"},"/appartement/huren/rotterdam/lombardkade/46239313":{"distance":6,"hasDetails":true,"bedroomCount":2,"peopleCount":2,"price":2450,"roomPrice":1225,"responded":false,"concerningTexts":[{"index":13,"concerningText":"student","concerningSentence":"If you are a student we need a school registration, employment agreement, salary slips of the guarantor, and a copy of the ID of your guarantor and yourself"}],"suitable":false,"email":"info@rivarentals.com","title":"Appartement Lombardkade"},"/appartement/huren/rotterdam/straatweg/46250113":{"distance":6,"hasDetails":true,"bedroomCount":2,"peopleCount":2,"price":1175,"roomPrice":587.5,"responded":true,"concerningTexts":[],"suitable":true,"email":"info@realestate.nl","title":"Appartement Straatweg"},"/appartement/huren/rotterdam/straatweg/46249949":{"distance":6,"hasDetails":true,"bedroomCount":2,"peopleCount":2,"price":1175,"roomPrice":587.5,"responded":true,"concerningTexts":[],"suitable":true,"email":"info@realestate.nl","title":"Appartement Straatweg"},"/appartement/huren/rotterdam/karel-doormanstraat/46242073":{"distance":6,"hasDetails":true,"bedroomCount":1,"peopleCount":1,"price":1100,"roomPrice":1100,"responded":false,"concerningTexts":[],"suitable":false,"email":"verhuur@kolpavvs.nl","title":"Appartement Karel Doormanstraat"},"/appartement/huren/den-haag/oranjestraat/46241579":{"distance":6,"hasDetails":true,"bedroomCount":2,"peopleCount":2,"price":2000,"roomPrice":1000,"responded":false,"concerningTexts":[],"suitable":false,"email":"info@immovita.nl","title":"Appartement Oranjestraat"},"/appartement/huren/rotterdam/kruiskade/46193110":{"distance":6,"hasDetails":true,"bedroomCount":2,"peopleCount":2,"price":1785,"roomPrice":892.5,"responded":false,"concerningTexts":[],"suitable":false,"email":"info@rentanapartment.nl","title":"Appartement Kruiskade"},"/appartement/huren/rotterdam/kruiskade/46192016":{"distance":6,"hasDetails":true,"bedroomCount":1,"peopleCount":1,"price":1250,"roomPrice":1250,"responded":false,"concerningTexts":[],"suitable":false,"email":"info@vhpn.nl","title":"Appartement Kruiskade"},"/appartement/huren/rotterdam/kruiskade/46189878":{"distance":6,"hasDetails":true,"bedroomCount":1,"peopleCount":1,"price":1250,"roomPrice":1250,"responded":false,"concerningTexts":[],"suitable":false,"email":"info@rentanapartment.nl","title":"Appartement Kruiskade"},"/appartement/huren/voorburg/balen-van-andelplein/46241126":{"distance":6,"hasDetails":true,"bedroomCount":2,"peopleCount":2,"price":1500,"roomPrice":750,"responded":false,"concerningTexts":[],"suitable":true,"email":"info@homelandmail.nl","title":"Appartement Balen van Andelplein"},"/appartement/huren/schiedam/parkweg/46240564":{"distance":6,"hasDetails":true,"bedroomCount":2,"peopleCount":2,"price":1400,"roomPrice":700,"responded":false,"concerningTexts":[],"suitable":true,"email":"hc_bakker@hotmail.com","title":"Appartement Parkweg"},"/appartement/huren/den-haag/esperantostraat/46240310":{"distance":6,"hasDetails":true,"bedroomCount":0,"peopleCount":1,"price":775,"roomPrice":775,"responded":false,"concerningTexts":[],"suitable":false,"email":"info@karensrealestate.nl","title":"Appartement Esperantostraat"},"/appartement/huren/den-haag/fluwelen-burgwal/46225958":{"distance":6,"hasDetails":true,"bedroomCount":2,"peopleCount":2,"price":1995,"roomPrice":997.5,"responded":false,"concerningTexts":[{"index":84,"concerningText":"couple","concerningSentence":"Beautiful flooring and modern stylish furniture make this an excellent choice for a couple or small family that wishes to live in the city centre with all the nice restaurants and shops just outside of the door"},{"index":84,"concerningText":"couple","concerningSentence":"Beautiful flooring and modern stylish furniture make this an excellent choice for a couple or small family that wishes to live in the city centre with all the nice restaurants and shops just outside of the door"}],"suitable":false,"email":"rentals@trechousing.nl","title":"Appartement Fluwelen Burgwal"},"/appartement/huren/rotterdam/burgemeester-meineszlaan/46222897":{"distance":6,"hasDetails":true,"bedroomCount":4,"peopleCount":3,"price":2500,"roomPrice":833.3333333333334,"responded":false,"concerningTexts":[],"suitable":false,"email":"info@rent2you.nl","title":"Appartement Burgemeester Meineszlaan"},"/appartement/huren/den-haag/emmapark/46253207":{"distance":7,"hasDetails":true,"bedroomCount":1,"peopleCount":1,"price":1195,"roomPrice":1195,"responded":false,"concerningTexts":[],"suitable":false,"email":"denhaag@tweelwonen.nl","title":"Appartement Emmapark"},"/appartement/huren/den-haag/emmapark/46253145":{"distance":7,"hasDetails":true,"bedroomCount":1,"peopleCount":1,"price":1195,"roomPrice":1195,"responded":false,"concerningTexts":[],"suitable":false,"email":"leiden@tweelwonen.nl","title":"Appartement Emmapark"},"/appartement/huren/den-haag/messchaertstraat/46253151":{"distance":7,"hasDetails":true,"bedroomCount":2,"peopleCount":2,"price":1325,"roomPrice":662.5,"responded":false,"suitable":true,"email":"info@karensrealestate.nl","concerningTexts":[],"title":"Appartement Messchaertstraat"},"/appartement/huren/rotterdam/boompjes/46252654":{"distance":7,"hasDetails":true,"bedroomCount":2,"peopleCount":2,"price":1750,"roomPrice":875,"responded":false,"concerningTexts":[],"suitable":false,"email":"info@rivarentals.com","title":"Appartement Boompjes"},"/appartement/huren/den-haag/anna-paulownastraat/46252631":{"distance":7,"hasDetails":true,"bedroomCount":3,"peopleCount":3,"price":3250,"roomPrice":1083.3333333333333,"responded":false,"concerningTexts":[],"suitable":false,"email":"home@number12.nl","title":"Appartement Anna Paulownastraat"},"/appartement/huren/rotterdam/franselaan/46248620":{"distance":7,"hasDetails":true,"bedroomCount":4,"peopleCount":4,"price":1750,"roomPrice":437.5,"responded":true,"concerningTexts":[],"suitable":true,"email":"info@realestate.nl","title":"Appartement Franselaan"},"/appartement/huren/rotterdam/mathenesserlaan/46253042":{"distance":7,"hasDetails":true,"bedroomCount":2,"peopleCount":2,"price":1575,"roomPrice":787.5,"responded":false,"concerningTexts":[{"index":67,"concerningText":"deler","concerningSentence":"• Bewoning is mogelijk voor maximaal 2 personen, een stel of woningdelers"}],"suitable":false,"email":"info@rentanapartment.nl","title":"Appartement Mathenesserlaan"},"/appartement/huren/den-haag/van-de-spiegelstraat/46253040":{"distance":7,"hasDetails":true,"bedroomCount":1,"peopleCount":1,"price":1050,"roomPrice":1050,"responded":false,"concerningTexts":[],"suitable":false,"email":"info@070wonen.nl","title":"Appartement Van De Spiegelstraat"},"/appartement/huren/rotterdam/middellandplein/46253021":{"distance":7,"hasDetails":true,"bedroomCount":1,"peopleCount":1,"price":965,"roomPrice":965,"responded":false,"concerningTexts":[],"suitable":false,"email":"info@vgwhousing.nl","title":"Appartement Middellandplein"},"/appartement/huren/rotterdam/jufferstraat/46253001":{"distance":7,"hasDetails":true,"bedroomCount":2,"peopleCount":2,"price":1650,"roomPrice":825,"responded":false,"concerningTexts":[],"suitable":false,"email":"info@rivarentals.com","title":"Appartement Jufferstraat"},"/appartement/huren/den-haag/jacob-gillesstraat/46252156":{"distance":7,"hasDetails":true,"bedroomCount":1,"peopleCount":1,"price":1395,"roomPrice":1395,"responded":false,"concerningTexts":[],"suitable":false,"email":"home@number12.nl","title":"Appartement Jacob Gillesstraat"},"/appartement/huren/schiedam/tuinlaan/46251577":{"distance":7,"hasDetails":true,"bedroomCount":3,"peopleCount":1,"price":2700,"roomPrice":2700,"responded":false,"concerningTexts":[],"suitable":false,"email":"rotterdam@tweelwonen.nl","title":"Appartement Tuinlaan"},"/appartement/huren/rotterdam/bierstraat/46250882":{"distance":7,"hasDetails":true,"bedroomCount":2,"peopleCount":2,"price":1450,"roomPrice":725,"responded":false,"suitable":true,"email":"info@rivarentals.com","concerningTexts":[],"title":"Appartement Bierstraat"},"/appartement/huren/schiedam/tuinlaan/46251434":{"distance":7,"hasDetails":true,"bedroomCount":3,"peopleCount":1,"price":2700,"roomPrice":2700,"responded":false,"concerningTexts":[],"suitable":false,"email":"rotterdam@tweelwonen.nl","title":"Appartement Tuinlaan"},"/appartement/huren/den-haag/bazarlaan/46251381":{"distance":7,"hasDetails":true,"bedroomCount":2,"peopleCount":2,"price":1495,"roomPrice":747.5,"responded":false,"concerningTexts":[],"suitable":true,"email":"info@immovita.nl","title":"Appartement Bazarlaan"},"/appartement/huren/rotterdam/wijnbrugstraat/46251252":{"distance":7,"hasDetails":true,"bedroomCount":2,"peopleCount":2,"price":2500,"roomPrice":1250,"responded":false,"concerningTexts":[],"suitable":false,"email":"linda@lindahousing.com","title":"Appartement Wijnbrugstraat"},"/appartement/huren/rotterdam/professor-poelslaan/46249176":{"distance":7,"hasDetails":true,"bedroomCount":3,"peopleCount":3,"price":1350,"roomPrice":450,"responded":true,"suitable":true,"email":"rentals@maashave.com","concerningTexts":[],"title":"Appartement Professor Poelslaan"},"/appartement/huren/rotterdam/boezemsingel/46249165":{"distance":7,"hasDetails":true,"bedroomCount":1,"peopleCount":1,"price":1195,"roomPrice":1195,"responded":false,"concerningTexts":[],"suitable":false,"email":"info@rentanapartment.nl","title":"Appartement Boezemsingel"},"/appartement/huren/den-haag/joan-maetsuyckerstraat/46249069":{"distance":7,"hasDetails":true,"bedroomCount":1,"peopleCount":1,"price":1095,"roomPrice":1095,"responded":false,"concerningTexts":[],"suitable":false,"email":"info@jmverhuur.nl","title":"Appartement Joan Maetsuyckerstraat"},"/appartement/huren/den-haag/balistraat/46250421":{"distance":7,"hasDetails":true,"bedroomCount":2,"peopleCount":2,"price":2200,"roomPrice":1100,"responded":false,"concerningTexts":[],"suitable":false,"email":"rentals@trechousing.nl","title":"Appartement Balistraat"},"/appartement/huren/rotterdam/boompjes/46252766":{"distance":7,"hasDetails":true,"bedroomCount":2,"peopleCount":2,"price":2200,"roomPrice":1100,"responded":false,"concerningTexts":[],"suitable":false,"email":"info@rotterdamrent.com","title":"Appartement Boompjes"},"/appartement/huren/den-haag/2e-sweelinckstraat/46247304":{"distance":7,"hasDetails":true,"bedroomCount":2,"peopleCount":2,"price":1650,"roomPrice":825,"responded":false,"concerningTexts":[],"suitable":false,"email":"info@homelandmail.nl","title":"Appartement 2e Sweelinckstraat"},"/appartement/huren/rotterdam/russischestraat/46247041":{"distance":7,"hasDetails":true,"bedroomCount":2,"peopleCount":2,"price":1450,"roomPrice":725,"responded":false,"concerningTexts":[],"suitable":true,"email":"info@i-housing.com","title":"Appartement Russischestraat"},"/appartement/huren/rotterdam/houtlaan/46088807":{"distance":7,"hasDetails":true,"bedroomCount":1,"peopleCount":1,"price":1400,"roomPrice":1400,"responded":false,"concerningTexts":[],"suitable":false,"email":"menno@askthem.nl","title":"Appartement Houtlaan"},"/appartement/huren/rotterdam/houtlaan/46243042":{"distance":7,"hasDetails":true,"bedroomCount":3,"peopleCount":3,"price":3750,"roomPrice":1250,"responded":false,"concerningTexts":[{"index":13,"concerningText":"student","concerningSentence":"If you are a student we need a school registration, employment agreement, salary slips of the guarantor, and a copy of the ID of your guarantor and yourself"}],"suitable":false,"email":"info@rivarentals.com","title":"Appartement Houtlaan"},"/appartement/huren/rotterdam/grote-visserijstraat/46242952":{"distance":7,"hasDetails":true,"bedroomCount":4,"peopleCount":4,"price":2500,"roomPrice":625,"responded":false,"suitable":true,"email":"info@vastgoedunie.com","concerningTexts":[],"title":"Appartement Grote Visserijstraat"},"/appartement/huren/den-haag/pluvierstraat/46242817":{"distance":7,"hasDetails":true,"bedroomCount":2,"peopleCount":2,"price":1450,"roomPrice":725,"responded":false,"concerningTexts":[],"suitable":true,"email":"info@homelandmail.nl","title":"Appartement Pluvierstraat"},"/appartement/huren/rotterdam/ochterveltstraat/46248490":{"distance":7,"hasDetails":true,"bedroomCount":1,"peopleCount":1,"price":1150,"roomPrice":1150,"responded":false,"concerningTexts":[],"suitable":false,"email":"info@vhpn.nl","title":"Appartement Ochterveltstraat"},"/appartement/huren/rotterdam/s-gravendijkwal/46248368":{"distance":7,"hasDetails":true,"bedroomCount":2,"peopleCount":2,"price":1295,"roomPrice":647.5,"responded":false,"concerningTexts":[],"suitable":true,"email":"info@vhpn.nl","title":"Appartement 's-Gravendijkwal"},"/appartement/huren/rotterdam/volmarijnstraat/46244476":{"distance":7,"hasDetails":true,"bedroomCount":2,"peopleCount":2,"price":1700,"roomPrice":850,"responded":false,"concerningTexts":[],"suitable":false,"email":"info@vastgoedunie.com","title":"Appartement Volmarijnstraat"},"/appartement/huren/den-haag/denneweg/46244480":{"distance":7,"hasDetails":true,"bedroomCount":2,"peopleCount":2,"price":2350,"roomPrice":1175,"responded":false,"concerningTexts":[],"suitable":false,"email":"info@homelandmail.nl","title":"Appartement Denneweg"},"/appartement/huren/rotterdam/deensestraat/46240112":{"distance":7,"hasDetails":true,"bedroomCount":1,"peopleCount":1,"price":765,"roomPrice":765,"responded":false,"concerningTexts":[],"suitable":false,"email":"verhuur@kolpavvs.nl","title":"Appartement Deensestraat"},"/appartement/huren/rotterdam/jaffa/46241975":{"distance":7,"hasDetails":true,"bedroomCount":4,"peopleCount":4,"price":3200,"roomPrice":800,"responded":false,"concerningTexts":[],"suitable":false,"email":"info@rotterdamrent.com","title":"Appartement Jaffa"},"/appartement/huren/den-haag/haverkamp/46244796":{"distance":7,"hasDetails":true,"bedroomCount":1,"peopleCount":1,"price":1195,"roomPrice":1195,"responded":false,"concerningTexts":[],"suitable":false,"email":"info@homelandmail.nl","title":"Appartement Haverkamp"},"/appartement/huren/den-haag/hendrinaland/46247912":{"distance":7,"hasDetails":true,"bedroomCount":3,"peopleCount":3,"price":1695,"roomPrice":565,"responded":true,"concerningTexts":[],"suitable":true,"email":"home@number12.nl","title":"Appartement Hendrinaland"},"/appartement/huren/rotterdam/poolsestraat/46247768":{"distance":7,"hasDetails":true,"bedroomCount":3,"peopleCount":3,"price":895,"roomPrice":298.3333333333333,"responded":true,"concerningTexts":[],"suitable":true,"email":"verhuur@kolpavvs.nl","title":"Appartement Poolsestraat"},"/appartement/huren/den-haag/jacob-gillesstraat/46241656":{"distance":7,"hasDetails":true,"bedroomCount":1,"peopleCount":1,"price":1395,"roomPrice":1395,"responded":false,"concerningTexts":[],"suitable":false,"email":"info@karensrealestate.nl","title":"Appartement Jacob Gillesstraat"},"/appartement/huren/zoetermeer/europaweg/46241542":{"distance":7,"hasDetails":true,"bedroomCount":1,"peopleCount":1,"price":850,"roomPrice":850,"responded":false,"concerningTexts":[],"suitable":false,"email":"verhuur@kolpavvs.nl","title":"Appartement Europaweg"},"/appartement/huren/rotterdam/grote-visserijstraat/46211702":{"distance":7,"hasDetails":true,"bedroomCount":1,"peopleCount":1,"price":890,"roomPrice":890,"responded":false,"concerningTexts":[{"index":88,"concerningText":"couple","concerningSentence":"bedroom apartment will be available on the Grote Visserijstraat which is suitable for a couple or for one person"}],"suitable":false,"email":"rotterdam@tweelwonen.nl","title":"Appartement Grote Visserijstraat"},"/appartement/huren/schiedam/boerhaavelaan/46211549":{"distance":7,"hasDetails":true,"bedroomCount":2,"peopleCount":2,"price":1195,"roomPrice":597.5,"responded":false,"concerningTexts":[],"suitable":true,"email":"rotterdam@tweelwonen.nl","title":"Appartement Boerhaavelaan"},"/appartement/huren/rotterdam/churchillplein/46246707":{"distance":7,"hasDetails":true,"bedroomCount":2,"peopleCount":2,"price":1750,"roomPrice":875,"responded":false,"concerningTexts":[],"suitable":false,"email":"info@rentanapartment.nl","title":"Appartement Churchillplein"},"/appartement/huren/den-haag/van-slingelandtstraat/46246678":{"distance":7,"hasDetails":true,"bedroomCount":2,"peopleCount":2,"price":1895,"roomPrice":947.5,"responded":false,"concerningTexts":[],"suitable":false,"email":"rentals@trechousing.nl","title":"Appartement Van Slingelandtstraat"},"/appartement/huren/den-haag/beethovenlaan/46238795":{"distance":7,"hasDetails":true,"bedroomCount":1,"peopleCount":1,"price":1195,"roomPrice":1195,"responded":false,"concerningTexts":[],"suitable":false,"email":"info@homelandmail.nl","title":"Appartement Beethovenlaan"},"/appartement/huren/rotterdam/william-boothlaan/46246599":{"distance":7,"hasDetails":true,"bedroomCount":3,"peopleCount":3,"price":1495,"roomPrice":498.3333333333333,"responded":true,"concerningTexts":[],"suitable":true,"email":"info@jecorental.nl","title":"Appartement William Boothlaan"},"/appartement/huren/rotterdam/hoogstraat/46246541":{"distance":7,"hasDetails":true,"bedroomCount":3,"peopleCount":3,"price":2200,"roomPrice":733.3333333333334,"responded":false,"concerningTexts":[],"suitable":true,"email":"info@rotterdamrent.com","title":"Appartement Hoogstraat"},"/appartement/huren/den-haag/zeestraat/46148142":{"distance":7,"hasDetails":true,"bedroomCount":2,"peopleCount":2,"price":2450,"roomPrice":1225,"responded":false,"concerningTexts":[],"suitable":false,"email":"info@wobeco.com","title":"Appartement Zeestraat"},"/appartement/huren/den-haag/wassenaarseweg/46147139":{"distance":7,"hasDetails":true,"bedroomCount":1,"peopleCount":1,"price":1150,"roomPrice":1150,"responded":false,"concerningTexts":[],"suitable":false,"email":"info@homelandmail.nl","title":"Appartement Wassenaarseweg"},"/appartement/huren/schiedam/jan-steenstraat/46115233":{"distance":7,"hasDetails":true,"bedroomCount":1,"peopleCount":1,"price":1075,"roomPrice":1075,"responded":false,"concerningTexts":[],"suitable":false,"email":"info@jecorental.nl","title":"Appartement Jan Steenstraat"},"/appartement/huren/den-haag/willem-de-zwijgerlaan/46068296":{"distance":7,"hasDetails":true,"bedroomCount":4,"peopleCount":4,"price":3250,"roomPrice":812.5,"responded":false,"concerningTexts":[],"suitable":false,"email":"info@homelandmail.nl","title":"Appartement Willem de Zwijgerlaan"},"/appartement/huren/rotterdam/paradijslaan/46227628":{"distance":7,"hasDetails":true,"bedroomCount":2,"peopleCount":2,"price":1100,"roomPrice":550,"responded":true,"concerningTexts":[],"suitable":true,"email":"info@realestate.nl","title":"Appartement Paradijslaan"},"/appartement/huren/den-haag/hooikade/46176344":{"distance":7,"hasDetails":true,"bedroomCount":2,"peopleCount":2,"price":3400,"roomPrice":1700,"responded":false,"concerningTexts":[],"suitable":false,"email":"info@homelandmail.nl","title":"Appartement Hooikade"},"/appartement/huren/den-haag/zeestraat/46176145":{"distance":7,"hasDetails":true,"bedroomCount":2,"peopleCount":2,"price":2700,"roomPrice":1350,"responded":false,"concerningTexts":[],"suitable":false,"email":"info@wobeco.com","title":"Appartement Zeestraat"},"/appartement/huren/den-haag/balistraat/46245710":{"distance":7,"hasDetails":true,"bedroomCount":2,"peopleCount":2,"price":1995,"roomPrice":997.5,"responded":false,"concerningTexts":[],"suitable":false,"email":"rentals@trechousing.nl","title":"Appartement Balistraat"},"/appartement/huren/rotterdam/nieuwe-binnenweg/46211045":{"distance":7,"hasDetails":true,"bedroomCount":2,"peopleCount":2,"price":1100,"roomPrice":550,"responded":true,"suitable":true,"email":"verhuur@kolpavvs.nl","concerningTexts":[],"title":"Appartement Nieuwe Binnenweg"},"/appartement/huren/rotterdam/halvemaanpassage/46207641":{"distance":7,"hasDetails":true,"bedroomCount":3,"peopleCount":3,"price":2600,"roomPrice":866.6666666666666,"responded":false,"concerningTexts":[{"index":13,"concerningText":"student","concerningSentence":"If you are a student we need a school registration, employment agreement, salary slips of the guarantor, and a copy of the ID of your guarantor and yourself"}],"suitable":false,"email":"info@rivarentals.com","title":"Appartement Halvemaanpassage"},"/appartement/huren/rotterdam/wijnbrugstraat/46203949":{"distance":7,"hasDetails":true,"bedroomCount":2,"peopleCount":2,"price":2050,"roomPrice":1025,"responded":false,"concerningTexts":[],"suitable":false,"email":"info@homelandmail.nl","title":"Appartement Wijnbrugstraat"},"/appartement/huren/rotterdam/mathenesserlaan/46192063":{"distance":7,"hasDetails":true,"bedroomCount":1,"peopleCount":1,"price":1650,"roomPrice":1650,"responded":false,"concerningTexts":[],"suitable":false,"email":"verhuur@kolpavvs.nl","title":"Appartement Mathenesserlaan"},"/appartement/huren/rotterdam/robert-baeldestraat/46246230":{"distance":7,"hasDetails":true,"bedroomCount":2,"peopleCount":2,"price":995,"roomPrice":497.5,"responded":true,"concerningTexts":[],"suitable":true,"email":"verhuur@kolpavvs.nl","title":"Appartement Robert Baeldestraat"},"/appartement/huren/den-haag/zeestraat/46188696":{"distance":7,"hasDetails":true,"bedroomCount":2,"peopleCount":2,"price":2400,"roomPrice":1200,"responded":false,"concerningTexts":[],"suitable":false,"email":"info@wobeco.com","title":"Appartement Zeestraat"},"/appartement/huren/rotterdam/van-vollenhovenstraat/46240379":{"distance":7,"hasDetails":true,"bedroomCount":2,"peopleCount":2,"price":1695,"roomPrice":847.5,"responded":false,"concerningTexts":[],"suitable":false,"email":"info@rivarentals.com","title":"Appartement Van Vollenhovenstraat"},"/appartement/huren/den-haag/zeestraat/46233518":{"distance":7,"hasDetails":true,"bedroomCount":2,"peopleCount":2,"price":2950,"roomPrice":1475,"responded":false,"concerningTexts":[],"suitable":false,"email":"home@number12.nl","title":"Appartement Zeestraat"},"/appartement/huren/rotterdam/schumannlaan/46233041":{"distance":7,"hasDetails":true,"bedroomCount":3,"peopleCount":3,"price":1350,"roomPrice":450,"responded":false,"concerningTexts":[],"suitable":true,"email":"vliegenthartmakelaardij@gmail.com","title":"Appartement Schumannlaan"},"/appartement/huren/rotterdam/hoge-boezem/46232732":{"distance":7,"hasDetails":true,"bedroomCount":2,"peopleCount":2,"price":1510,"roomPrice":755,"responded":false,"concerningTexts":[{"index":8,"concerningText":"student","concerningSentence":"Delende studenten zijn niet toegestaan"},{"index":8,"concerningText":"student","concerningSentence":"Sharing students are not allowed"}],"suitable":false,"email":"rotterdam@tweelwonen.nl","title":"Appartement Hoge Boezem"},"/appartement/huren/rotterdam/maaskade/46235528":{"distance":7,"hasDetails":true,"bedroomCount":1,"peopleCount":1,"price":1675,"roomPrice":1675,"responded":false,"concerningTexts":[],"suitable":false,"email":"rentals@maashave.com","title":"Appartement Maaskade"},"/appartement/huren/rotterdam/witte-de-withstraat/46220373":{"distance":7,"hasDetails":true,"bedroomCount":1,"peopleCount":1,"price":1295,"roomPrice":1295,"responded":false,"concerningTexts":[],"suitable":false,"email":"verhuur@kolpavvs.nl","title":"Appartement Witte de Withstraat"},"/appartement/huren/rotterdam/hoge-boezem/46219064":{"distance":7,"hasDetails":true,"bedroomCount":2,"peopleCount":2,"price":1525,"roomPrice":762.5,"responded":false,"concerningTexts":[{"index":8,"concerningText":"student","concerningSentence":"Delende studenten zijn niet toegestaan"},{"index":8,"concerningText":"student","concerningSentence":"Sharing students are not allowed"}],"suitable":false,"email":"rotterdam@tweelwonen.nl","title":"Appartement Hoge Boezem"},"/appartement/huren/rotterdam/hoge-boezem/46219041":{"distance":7,"hasDetails":true,"bedroomCount":2,"peopleCount":2,"price":1525,"roomPrice":762.5,"responded":false,"concerningTexts":[{"index":8,"concerningText":"student","concerningSentence":"Delende studenten zijn niet toegestaan"},{"index":8,"concerningText":"student","concerningSentence":"Sharing students are not allowed"}],"suitable":false,"email":"rotterdam@tweelwonen.nl","title":"Appartement Hoge Boezem"}}